middleman_ai/__init__.py
middleman_ai/__main__.py
middleman_ai/client.py
middleman_ai/exceptions.py
middleman_ai/models.py
middleman_ai/py.typed
middleman_ai/cli/__init__.py
middleman_ai/cli/main.py
middleman_ai/mcp/__init__.py
middleman_ai/mcp/server.py
middleman_ai-0.3.1.dist-info/LICENSE
middleman_ai-0.3.1.dist-info/METADATA
middleman_ai-0.3.1.dist-info/WHEEL
middleman_ai-0.3.1.dist-info/entry_points.txt
middleman_ai-0.3.1.dist-info/top_level.txt
middleman_ai-0.3.1.dist-info/RECORD
