Metadata-Version: 2.2
Name: middleman-ai
Version: 0.3.1
Summary: Python client SDK for Middleman.ai API
Home-page: https://github.com/GenerativeAgents/middleman-sdk
Author: Generative Agents, Inc.
License: MIT
Requires-Python: >=3.10
License-File: LICENSE
Requires-Dist: requests>=2
Requires-Dist: pydantic>=2
Requires-Dist: typing-extensions
Requires-Dist: click>=8.0.0
Requires-Dist: mcp[cli]>=1.6.0
